spinitron/client.py
spinitron/config.py
spinitron/endpoint.py
spinitron/models/Base.py
spinitron/models/Factory.py
spinitron/models/Listing.py
spinitron/models/Persona.py
spinitron/models/Playlist.py
spinitron/models/Show.py
spinitron/models/Spin.py
spinitron/models/__init__.py
spinitron/session.py
spinitron-0.1.0.dist-info/WHEEL
spinitron-0.1.0.dist-info/METADATA
spinitron-0.1.0.dist-info/RECORD
